[
  {
    "path": "talks/2021-03-22-conversations-about-sleep-clinical-data-wrangling/",
    "title": "Conversations about Sleep: Clinical Data Wrangling",
    "description": "Talk given for AMIA Informatics Educators Meeting about our clinical data wrangling workshop.",
    "author": [
      {
        "name": "Ted Laderas",
        "url": {}
      }
    ],
    "date": "2021-03-22",
    "categories": [],
    "contents": "\r\n\r\n\r\n\r\n\r\n\r\n\r\n\r\n",
    "preview": {},
    "last_modified": "2021-03-22T14:55:43-07:00",
    "input_file": {}
  },
  {
    "path": "talks/2021-03-22-psychological-safety/",
    "title": "Psychological Safety",
    "description": "Slides talking about the importance of psychological safety and codes of conduct in the classroom.",
    "author": [
      {
        "name": "Ted Laderas",
        "url": {}
      }
    ],
    "date": "2021-03-22",
    "categories": [],
    "contents": "\r\n\r\n\r\n\r\n\r\n\r\n\r\n\r\n",
    "preview": {},
    "last_modified": "2021-03-22T11:21:24-07:00",
    "input_file": {}
  },
  {
    "path": "talks/2021-03-22-the-md-in-rmd-teaching-clinicians-analytics-usin-r/",
    "title": "The MD in .Rmd: Teaching Clinicians Analytics using R",
    "description": "A talk given for R/Medicine 2020 about our Data Analytics course.",
    "author": [
      {
        "name": "Ted Laderas",
        "url": {}
      }
    ],
    "date": "2021-03-22",
    "categories": [],
    "contents": "\r\n\r\n\r\n\r\n\r\n\r\n\r\n\r\n",
    "preview": {},
    "last_modified": "2021-03-22T15:06:02-07:00",
    "input_file": {}
  },
  {
    "path": "talks/2021-03-20-data-storytelling/",
    "title": "Data Storytelling",
    "description": "Learn about tailoring your visualization to an audience through reducing cognitive load.",
    "author": [
      {
        "name": "Ted Laderas",
        "url": {}
      }
    ],
    "date": "2021-03-20",
    "categories": [],
    "contents": "\r\n\r\n\r\n\r\n\r\n\r\n\r\n\r\n",
    "preview": {},
    "last_modified": "2021-03-22T11:22:41-07:00",
    "input_file": {}
  },
  {
    "path": "talks/2021-03-22-object-oriented-systems-in-r/",
    "title": "Object Oriented Systems in R",
    "description": "A short description of the post.",
    "author": [
      {
        "name": "Ted Laderas",
        "url": {}
      },
      {
        "name": "Scott Chamberlain",
        "url": {}
      }
    ],
    "date": "2019-05-21",
    "categories": [],
    "contents": "\r\nDescription\r\nThis is a talk/workshop summarizing three different object oriented programming systems in R: S3, S4, and R6. It is meant for intermediate R Programmers.\r\nThis talk contains two notebooks explaining S4 and R6 that can be found at the repository link below.\r\nIntroductory Slides\r\n\r\n\r\n\r\n\r\nLinks\r\nWorkshop Repository\r\n\r\n\r\n\r\n",
    "preview": {},
    "last_modified": "2021-03-22T14:52:28-07:00",
    "input_file": {}
  },
  {
    "path": "talks/2021-03-20-system-science-and-data-science/",
    "title": "System Science and Data Science",
    "description": "How are System Science and Data Science connected?",
    "author": [
      {
        "name": "Ted Laderas",
        "url": {}
      }
    ],
    "date": "2018-02-15",
    "categories": [],
    "contents": "\r\n\r\n\r\n\r\n\r\n\r\n\r\n\r\n",
    "preview": {},
    "last_modified": "2021-03-20T20:56:34-07:00",
    "input_file": {}
  }
]
